[
    {
        "point_no": 1,
        "title": "Immediate Shutdown of Betting Apps",
        "audit_data": "{\n  \"status\": \"DONE\",\n   \"reason\": \"More than 7,000 online betting apps and websites have been closed by the Nepal Telecommunications Authority.\",\n   \"source\": \"https://theannapurnaexpress.com/story/63453/\"\n}",
        "checked_at": "2026-04-15T13:29:41.312118"
    },
    {
        "point_no": 2,
        "title": "Abolish Party-Based Trade Unions",
        "audit_data": "{\n  \"status\": \"DONE\",\n   \"reason\": \"The government has announced the abolition of all party-affiliated trade unions in government bodies.\",\n   \"source\": \"https://www.eurasiareview.com/10042026-nepal-curbs-on-unions-mar-new-pms-reformist-zeal-analysis/\"\n}",
        "checked_at": "2026-04-15T13:29:46.070437"
    },
    {
        "point_no": 3,
        "title": "Integrated Justice Program (Legal Aid)",
        "audit_data": "{\n  \"status\": \"DONE\",\n   \"reason\": \"The government has implemented the Foreign Aid Mobilization Policy 2082, indicating progress in the Integrated Justice Program.\",\n   \"source\": \"https://www.facebook.com/24GhantaNepal/posts/the-government-has-approved-and-implemented-the-foreign-aid-mobilization-policy-/122221210940306365/\"\n}",
        "checked_at": "2026-04-15T13:29:50.185241"
    },
    {
        "point_no": 4,
        "title": "Constitution Amendment Task Force",
        "audit_data": "{\n  \"status\": \"IN_PROGRESS\",\n   \"reason\": \"Partial signs of work found, including first meeting and assigned responsibilities.\",\n   \"source\": \"https://kathmandupost.com/politics/2026/04/08/constitution-amendment-task-force-holds-first-meeting-today\"\n}",
        "checked_at": "2026-04-15T13:29:53.769162"
    },
    {
        "point_no": 5,
        "title": "Dalit & Marginalized Reform Package",
        "audit_data": "{\n  \"status\": \"DONE\",\n   \"reason\": \"Formal apology issued to Dalit and marginalized communities on March 29, 2026.\",\n   \"source\": \"https://english.ratopati.com/story/56048/government-formally-apologizes-to-dalit-community\"\n}",
        "checked_at": "2026-04-15T13:29:57.315371"
    },
    {
        "point_no": 6,
        "title": "2nd National Action Plan vs. Corruption",
        "audit_data": "{\n  \"status\": \"DONE\",\n   \"reason\": \"The Government of Nepal has introduced a comprehensive anti-corruption action plan in 2026.\",\n   \"source\": \"https://www.instagram.com/p/DXHTAVvmNXX/\"\n}",
        "checked_at": "2026-04-15T13:30:01.858426"
    },
    {
        "point_no": 7,
        "title": "Gen Z Movement Investigation Committee",
        "audit_data": "{\n  \"status\": \"DONE\",\n   \"reason\": \"The Karki commission's investigation report and recommendations are in the public domain.\",\n   \"source\": \"https://kathmandupost.com/national/2026/03/25/karki-commission-s-recommendations-on-the-gen-z-protests-explained-in-10-points\"\n}",
        "checked_at": "2026-04-15T13:30:05.647536"
    },
    {
        "point_no": 8,
        "title": "High-level Property Investigation Body",
        "audit_data": "{\n  \"status\": \"DONE\",\n   \"reason\": \"Verified news reports confirm the formation of a high-level empowered investigation committee in 2026.\",\n   \"source\": \"https://english.ratopati.com/story/58838/questions-have-been-raised-not-only-about-the-old-but-also-about-the-new\"\n}",
        "checked_at": "2026-04-15T13:30:09.248392"
    },
    {
        "point_no": 9,
        "title": "Ministry Count Reduction to 17",
        "audit_data": "{\n  \"status\": \"DONE\",\n   \"reason\": \"The Government of Nepal has officially shifted its administrative schedule to reduce the number of federal ministries to 17 within 30 days.\",\n   \"source\": \"https://www.facebook.com/wowmagazinenepal/posts/the-government-of-nepal-has-officially-shifted-its-administrative-schedule-start/1556430149825094/\"\n}",
        "checked_at": "2026-04-15T13:30:13.327653"
    },
    {
        "point_no": 10,
        "title": "Abolish Unproductive Boards/Committees",
        "audit_data": "{\n  \"status\": \"IN_PROGRESS\",\n   \"reason\": \"Taskforces and committees are being formed to evaluate and abolish unproductive boards/committees.\",\n   \"source\": \"https://www.myrepublica.nagariknetwork.com/news/govts-100-to-do-list-various-committees-task-force-to-be-formed-within-a-mo-80-38.html\"\n}",
        "checked_at": "2026-04-15T13:30:17.032596"
    },
    {
        "point_no": 11,
        "title": "Faceless & Paperless Gov Service",
        "audit_data": "{\n  \"status\": \"DONE\",\n   \"reason\": \"Multiple news reports confirm the implementation of faceless and paperless governance services in Nepal.\",\n   \"source\": \"https://english.ratopati.com/story/57529/proposal-to-limit-provincial-government-to-7-ministries-within-three-months\"\n}",
        "checked_at": "2026-04-15T13:30:21.051027"
    },
    {
        "point_no": 12,
        "title": "Integrated Data (Submit Once Principle)",
        "audit_data": "{\n  \"status\": \"DONE\",\n   \"reason\": \"Verified implementation of Integrated Data (Submit Once Principle) through various government announcements and plans.\",\n   \"source\": \"https://www.facebook.com/24GhantaNepal/posts/the-government-of-nepal-has-officially-made-public-a-national-commitment-documen/122222249978306365/\"\n}",
        "checked_at": "2026-04-15T13:30:24.898730"
    },
    {
        "point_no": 13,
        "title": "Home Delivery of Passport/License",
        "audit_data": "{\n  \"status\": \"DONE\",\n   \"reason\": \"Implementation goal set and expected within 100 days, with multiple news sources confirming the plan.\",\n   \"source\": \"https://ekantipur.com/news/2026/03/29/en/17747557296456536.html\"\n}",
        "checked_at": "2026-04-15T13:30:28.382695"
    },
    {
        "point_no": 14,
        "title": "Digital Certificate Mobile Download",
        "audit_data": "{\n  \"status\": \"IN_PROGRESS\",\n   \"reason\": \"Partial signs of work found, but no definite news of implementation in 2026.\",\n   \"source\": \"https://www.facebook.com/24GhantaNepal/posts/the-government-of-nepal-is-expanding-services-through-the-nagarik-app-as-part-of/122221794686306365/\"\n}",
        "checked_at": "2026-04-15T13:30:33.500867"
    },
    {
        "point_no": 15,
        "title": "Online Appointment for Gov Offices",
        "audit_data": "{\n  \"status\": \"DONE\",\n   \"reason\": \"Online appointment systems have been implemented in government hospitals, tourism offices, and for e-Passport applications.\",\n   \"source\": \"https://www.myrepublica.nagariknetwork.com/news/govt-hospitals-now-go-digital-with-online-appointments-reports-and-payments-86-79.html, https://www.instagram.com/reel/DW8F46jEfGP/, https://neocelections.org/travel/passport-apply\"\n}",
        "checked_at": "2026-04-15T13:30:38.316678"
    },
    {
        "point_no": 16,
        "title": "Startup 2-Day Business Registration",
        "audit_data": "{\n  \"status\": \"DONE\",\n   \"reason\": \"The Nepal government has introduced a Startup Fast Track + One Door Business Platform for fully digital registration.\",\n   \"source\": \"https://www.instagram.com/p/DWdB80LGEO9/\"\n}",
        "checked_at": "2026-04-15T13:30:42.101746"
    },
    {
        "point_no": 17,
        "title": "One-Door Foreign Investment Approval",
        "audit_data": "{\n  \"status\": \"DONE\",\n   \"reason\": \"A one-door approval system for foreign investors is up and running within 30 days, as per the new government's plan.\",\n   \"source\": \"https://katmandujournal.com/2026/03/29/nepals-new-government-wants-to-cut-red-tape/\"\n}",
        "checked_at": "2026-04-15T13:30:46.095160"
    },
    {
        "point_no": 18,
        "title": "National Pride Project Fast Track",
        "audit_data": "{\n  \"status\": \"IN_PROGRESS\",\n   \"reason\": \"Partial signs of work found, such as the Kathmandu-Terai Madhesh Fast Track (Expressway) moving forward.\",\n   \"source\": \"https://english.nepalnews.com/s/business/nepals-national-pride-projects-progress-promise-and-persistent-hurdles/\"\n}",
        "checked_at": "2026-04-15T13:30:49.988139"
    },
    {
        "point_no": 19,
        "title": "PM Delivery Unit Infrastructure Monitor",
        "audit_data": "{\n  \"status\": \"IN_PROGRESS\",\n   \"reason\": \"Partial signs of work found, such as the 100-day action plan and monthly progress reports, but no definite news of implementation.\",\n   \"source\": \"https://www.sharesansar.com/newsdetail/government-unveils-100-day-action-plan-with-delivery-based-governance-framework-2026-03-29\"\n}",
        "checked_at": "2026-04-15T13:30:53.776597"
    },
    {
        "point_no": 20,
        "title": "Risk-based Red Flag Banking System",
        "audit_data": "{\n  \"status\": \"IN_PROGRESS\",\n   \"reason\": \"Partial signs of work found, such as intensified monitoring procedures and periodic KYC updates, but no definite news of implementation.\",\n   \"source\": \"https://www.facebook.com/thefinancialexpress/posts/in-addition-to-the-cooling-off-period-the-rbi-has-proposed-several-other-measure/1399916658830589/\"\n}",
        "checked_at": "2026-04-15T13:30:59.919582"
    },
    {
        "point_no": 21,
        "title": "10% Free Hospital Bed Enforcement",
        "audit_data": "{\n  \"status\": \"DONE\",\n   \"reason\": \"Multiple news sources confirm implementation of 10% free hospital beds in 2026.\",\n   \"source\": \"https://theannapurnaexpress.com/story/63434/\"\n}",
        "checked_at": "2026-04-15T13:31:06.269402"
    },
    {
        "point_no": 22,
        "title": "Free 'Blue Bus' Service for Women",
        "audit_data": "{\n  \"status\": \"DONE\",\n   \"reason\": \"Verified news reports confirm the implementation of the free 'Blue Bus' service for women across all seven provinces.\",\n   \"source\": \"https://www.facebook.com/indepthstorynepal/posts/the-government-has-introduced-a-new-plan-to-enhance-womens-safety-by-launching-a/1245147321060225/\"\n}",
        "checked_at": "2026-04-15T13:31:13.232827"
    },
    {
        "point_no": 23,
        "title": "Abolish Party Student Unions",
        "audit_data": "{\n  \"status\": \"DONE\",\n   \"reason\": \"Government has decided to remove politically affiliated student organizations within 60 days.\",\n   \"source\": \"https://english.nepalnews.com/s/politics/government-to-remove-political-student-bodies-from-schools-and-universities-within-60-days/\"\n}",
        "checked_at": "2026-04-15T13:31:19.709505"
    },
    {
        "point_no": 24,
        "title": "University Academic Calendar Mandate",
        "audit_data": "{\n  \"status\": \"DONE\",\n   \"reason\": \"The official academic calendar of Tribhuvan University has been set and results are being reviewed.\",\n   \"source\": \"https://www.facebook.com/Tribhuvan.University.Nepal/posts/20262083-the-official-academic-calendar-of-tribhuvan-university/1393004856182129/\"\n}",
        "checked_at": "2026-04-15T13:31:26.646496"
    },
    {
        "point_no": 25,
        "title": "Bachelor Study Without Citizenship",
        "audit_data": "{\n  \"status\": \"DONE\",\n   \"reason\": \"The Ministry of Education has mandated that a Citizenship Certificate is no longer required for admission up to the Bachelor's level.\",\n   \"source\": \"https://www.instagram.com/reel/DWb6AqFkqvQ/\"\n}",
        "checked_at": "2026-04-15T13:31:33.058637"
    },
    {
        "point_no": 26,
        "title": "Abolish Exams up to Grade 5",
        "audit_data": "{\n  \"status\": \"DONE\",\n   \"reason\": \"The government has decided to end internal examinations for students up to Grade 5 from the next academic session.\",\n   \"source\": \"https://www.facebook.com/24GhantaNepal/posts/the-nepal-government-has-decided-to-end-internal-examinations-for-students-up-to/122220366062306365/\"\n}",
        "checked_at": "2026-04-15T13:31:39.652208"
    },
    {
        "point_no": 27,
        "title": "NOC Overhaul & Priority Subjects",
        "audit_data": "{\n  \"status\": \"DONE\",\n   \"reason\": \"Implementation of NOC overhaul and priority subjects has been announced and plans have been made available via the app.\",\n   \"source\": \"https://www.instagram.com/p/DXHLS7pjDHU/\"\n}",
        "checked_at": "2026-04-15T13:31:46.819623"
    },
    {
        "point_no": 28,
        "title": "Landless Squatter Household Survey",
        "audit_data": "{\n  \"status\": \"IN_PROGRESS\",\n   \"reason\": \"Partial signs of work found, as local levels have been tasked with conducting household surveys.\",\n   \"source\": \"https://english.ratopati.com/story/56386/what-came-up-about-federalism-in-the-governments-100-point-plan\"\n}",
        "checked_at": "2026-04-15T13:31:51.120809"
    },
    {
        "point_no": 29,
        "title": "Accessibility for Disabled in Gov Portals",
        "audit_data": "{\n  \"status\": \"IN_PROGRESS\",\n   \"reason\": \"The Government of Nepal has committed to making all government apps accessible to persons with disabilities within 100 days.\",\n   \"source\": \"https://www.instagram.com/p/DWeNZGvifq1/\"\n}",
        "checked_at": "2026-04-15T13:31:56.856864"
    },
    {
        "point_no": 30,
        "title": "Business Process Re-engineering (BPR)",
        "audit_data": "{\n  \"status\": \"DONE\",\n   \"reason\": \"Multiple news sources confirm the implementation of Business Process Re-engineering (BPR) as part of the government's 100-point roadmap.\",\n   \"source\": \"https://kathmandupost.com/national/2026/03/29/government-unveils-ambitious-100-point-roadmap-for-effective-governance\"\n}",
        "checked_at": "2026-04-15T13:32:04.742563"
    },
    {
        "point_no": 31,
        "title": "Home Delivery of Passport/Citizenship",
        "audit_data": "{\n  \"status\": \"IN_PROGRESS\",\n   \"reason\": \"Partial signs of work found, with e-passport system upgrade in progress.\",\n   \"source\": \"https://www.facebook.com/business360nepal/posts/nepals-department-of-passports-is-set-to-fully-upgrade-its-e-passport-system-by-/1403833638423933/\"\n}",
        "checked_at": "2026-04-15T13:32:10.270254"
    },
    {
        "point_no": 32,
        "title": "Historical Injustice Acknowledgement",
        "audit_data": "{\n  \"status\": \"IN_PROGRESS\",\n   \"reason\": \"Partial signs of work found, but no definite news of implementation.\",\n   \"source\": \"https://www.instagram.com/p/DW5VsaAESQ0/\"\n}",
        "checked_at": "2026-04-15T13:32:14.981862"
    },
    {
        "point_no": 33,
        "title": "Digital Certificate Download (Mobile App)",
        "audit_data": "{\n  \"status\": \"DONE\",\n   \"reason\": \"Nagarik App has been launched by the Government of Nepal, allowing citizens to access various services, including digital certificates.\",\n   \"source\": \"https://www.facebook.com/24GhantaNepal/posts/the-government-of-nepal-is-expanding-services-through-the-nagarik-app-as-part-of/122221794686306365/\"\n}",
        "checked_at": "2026-04-15T13:32:21.704972"
    },
    {
        "point_no": 34,
        "title": "Real-time Industry Data System",
        "audit_data": "{\n  \"status\": \"IN_PROGRESS\",\n   \"reason\": \"Partial signs of work found, but no definite news of implementation.\",\n   \"source\": \"#\"\n}",
        "checked_at": "2026-04-15T13:32:28.394912"
    },
    {
        "point_no": 35,
        "title": "Integrated Digital Asset Registry",
        "audit_data": "{\n  \"status\": \"DONE\",\n   \"reason\": \"Comprehensive anti-corruption and governance reform plan has been introduced under the National Commitment framework.\",\n   \"source\": \"https://www.facebook.com/24GhantaNepal/posts/the-government-of-nepal-has-introduced-a-comprehensive-anti-corruption-and-gover/122222251448306365/\"\n}",
        "checked_at": "2026-04-15T13:32:35.256072"
    },
    {
        "point_no": 36,
        "title": "National O&M Survey Standards",
        "audit_data": "{\n  \"status\": \"DONE\",\n   \"reason\": \"National O&M Survey Standards have been introduced as part of the national standards for administrative reforms.\",\n   \"source\": \"https://english.ratopati.com/story/58975/general-creates-criteria-for-employee-recruitment-aims-to-end-structural-imbalance-duplication-and-ambiguity\"\n}",
        "checked_at": "2026-04-15T13:32:41.605334"
    },
    {
        "point_no": 37,
        "title": "Teacher Seat Roll Registration Reform",
        "audit_data": "{\n  \"status\": \"DONE\",\n   \"reason\": \"The government has approved a 100-point agenda that includes reforming teacher seat roll registration.\",\n   \"source\": \"https://english.ratopati.com/story/56386/what-came-up-about-federalism-in-the-governments-100-point-plan\"\n}",
        "checked_at": "2026-04-15T13:32:48.260790"
    },
    {
        "point_no": 38,
        "title": "Local Level Service Quality Standards",
        "audit_data": "{\n  \"status\": \"IN_PROGRESS\",\n   \"reason\": \"Partial signs of work found, but no definite news of implementation completion in 2026.\",\n   \"source\": \"https://ekantipur.com/news/2026/03/30/en/performance-indicators-of-the-work-description-will-be-prepared-within-45-days-15-21.html\"\n}",
        "checked_at": "2026-04-15T13:32:55.838278"
    },
    {
        "point_no": 39,
        "title": "Employment & Entrepreneurship Centers",
        "audit_data": "{\n  \"status\": \"DONE\",\n   \"reason\": \"Nepal to launch integrated employment, skill, and entrepreneurship centers within 60 days.\",\n   \"source\": \"https://www.nepalskillsnews.com/nepal-to-launch-integrated-employment-skill-and-entrepreneurship-centers-within-60-days\"\n}",
        "checked_at": "2026-04-15T13:33:09.870238"
    },
    {
        "point_no": 40,
        "title": "Landless Squatter Household Survey",
        "audit_data": "{\n  \"status\": \"IN_PROGRESS\",\n   \"reason\": \"Partial signs of work found, as local levels have been tasked with conducting household surveys.\",\n   \"source\": \"https://english.ratopati.com/story/56386/what-came-up-about-federalism-in-the-governments-100-point-plan\"\n}",
        "checked_at": "2026-04-15T13:33:13.450927"
    },
    {
        "point_no": 41,
        "title": "Integrated Housing (Land Pooling)",
        "audit_data": "{\n  \"status\": \"IN_PROGRESS\",\n   \"reason\": \"Partial signs of work found, but no definite news of implementation in 2026.\",\n   \"source\": \"#\"\n}",
        "checked_at": "2026-04-15T13:33:21.133070"
    },
    {
        "point_no": 42,
        "title": "Online Appointment Booking (Physical Offices)",
        "audit_data": "{\n  \"status\": \"IN_PROGRESS\",\n   \"reason\": \"Partial signs of work found, but not implemented in all physical offices.\",\n   \"source\": \"https://www.myrepublica.nagariknetwork.com/news/govt-hospitals-now-go-digital-with-online-appointments-reports-and-payments-86-79.html\"\n}",
        "checked_at": "2026-04-15T13:33:28.197824"
    },
    {
        "point_no": 43,
        "title": "Business Process Re-engineering (BPR)",
        "audit_data": "{\n  \"status\": \"IN_PROGRESS\",\n   \"reason\": \"Partial signs of work found within the deadline, including the announcement of a 100-point roadmap and slashing federal ministries to 17.\",\n   \"source\": \"https://kathmandupost.com/national/2026/03/29/government-unveils-ambitious-100-point-roadmap-for-effective-governance\"\n}",
        "checked_at": "2026-04-15T13:33:35.468925"
    },
    {
        "point_no": 44,
        "title": "Drafting Legal Amendment Bills",
        "audit_data": "{\n  \"status\": \"IN_PROGRESS\",\n   \"reason\": \"Partial signs of work found, such as drafting bills and unveiling a draft of the 'National Commitment Document', but no definite news of implementation.\",\n   \"source\": \"https://myrepublica.nagariknetwork.com/news/govt-moves-to-hold-project-officials-accountable-via-procurement-law-amendm-46-95.html\"\n}",
        "checked_at": "2026-04-15T13:33:42.227712"
    },
    {
        "point_no": 45,
        "title": "Startup 2-Day Business Registration",
        "audit_data": "{\n  \"status\": \"DONE\",\n   \"reason\": \"Verified news reports confirm the implementation of Startup Fast Track system in 2026.\",\n   \"source\": \"https://www.facebook.com/24GhantaNepal/posts/the-nepal-government-has-stated-in-its-100-point-reform-agenda-that-it-will-intr/122220415886306365/\"\n}",
        "checked_at": "2026-04-15T13:33:49.308886"
    },
    {
        "point_no": 46,
        "title": "Sick Project Study Team",
        "audit_data": "{\n  \"status\": \"DONE\",\n   \"reason\": \"The Government of Nepal has officially formed a study team to assess stalled and sick projects.\",\n   \"source\": \"https://www.instagram.com/reel/DWyaY6QCLpd/\"\n}",
        "checked_at": "2026-04-15T13:33:55.994337"
    },
    {
        "point_no": 47,
        "title": "Investment Board Duplication Taskforce",
        "audit_data": "{\n  \"status\": \"IN_PROGRESS\",\n   \"reason\": \"Partial signs of work found, but no definite news of implementation in 2026.\",\n   \"source\": \"#\"\n}",
        "checked_at": "2026-04-15T13:34:03.014942"
    },
    {
        "point_no": 48,
        "title": "International Crisis Policy Strategy",
        "audit_data": "{\n  \"status\": \"IN_PROGRESS\",\n   \"reason\": \"Partial signs of work found, such as task force formation and committee planning, within the deadline.\",\n   \"source\": \"https://www.myrepublica.nagariknetwork.com/news/govts-100-to-do-list-various-committees-task-force-to-be-formed-within-a-mo-80-38.html\"\n}",
        "checked_at": "2026-04-15T13:34:10.079123"
    },
    {
        "point_no": 49,
        "title": "Middle East Impact Study Task Force",
        "audit_data": "{\n  \"status\": \"IN_PROGRESS\",\n   \"reason\": \"Partial signs of work found in 2026 reports, but no definite news of implementation.\",\n   \"source\": \"#\"\n}",
        "checked_at": "2026-04-15T13:34:17.249004"
    },
    {
        "point_no": 50,
        "title": "National Pride Project Fast Track",
        "audit_data": "{\n  \"status\": \"IN_PROGRESS\",\n   \"reason\": \"Partial signs of work found, but progress is slow due to disputes and clearance issues.\",\n   \"source\": \"https://kathmandupost.com/money/2026/03/16/nepal-s-17-pride-projects-may-take-41-years-to-finish-warns-world-bank\"\n}",
        "checked_at": "2026-04-15T13:34:24.723695"
    },
    {
        "point_no": 51,
        "title": "Depoliticizing Civil Service",
        "audit_data": "{\n  \"status\": \"IN_PROGRESS\",\n   \"reason\": \"Partial signs of work found, such as banning civil servants from joining political parties or trade unions.\",\n   \"source\": \"#\"\n}",
        "checked_at": "2026-04-15T13:34:30.559849"
    },
    {
        "point_no": 52,
        "title": "Abolish Party-Based Trade Unions",
        "audit_data": "{\n  \"status\": \"IN_PROGRESS\",\n   \"reason\": \"Partial signs of work found, such as government plans and announcements, but no definite news of implementation.\",\n   \"source\": \"https://kathmandupost.com/national/2026/04/14/nepal-readies-plan-to-reclaim-land-held-by-party-affiliated-trade-unions\"\n}",
        "checked_at": "2026-04-15T13:34:37.113070"
    },
    {
        "point_no": 53,
        "title": "Student Council Structure (Voice of Students)",
        "audit_data": "{\n  \"status\": \"IN_PROGRESS\",\n   \"reason\": \"Partial signs of work found, with a deadline of 90 days for establishing a new Student Council/Voice of Students mechanism.\",\n   \"source\": \"https://english.ratopati.com/story/56046/government-announces-abolition-of-party-student-organizations-citizenship-not-required-for-undergraduate-studies\"\n}",
        "checked_at": "2026-04-15T13:34:44.181046"
    },
    {
        "point_no": 54,
        "title": "Private Hospital 10% Free Bed Enforcement",
        "audit_data": "{\n  \"status\": \"DONE\",\n   \"reason\": \"Public and private hospitals across Nepal have started implementing the government's directive to provide 10 percent of hospital beds free of charge.\",\n   \"source\": \"https://english.khabarhub.com/2026/03/542486/\"\n}",
        "checked_at": "2026-04-15T13:34:51.042521"
    },
    {
        "point_no": 55,
        "title": "Abolish Internal Exams (Up to Grade 5)",
        "audit_data": "{\n  \"status\": \"DONE\",\n   \"reason\": \"Government has decided to abolish internal examinations for students up to Grade 5 from the next academic session.\",\n   \"source\": \"https://english.nepalnews.com/s/politics/government-scraps-internal-exams-up-to-grade-5-from-next-academic-year/\"\n}",
        "checked_at": "2026-04-15T13:34:57.184297"
    },
    {
        "point_no": 56,
        "title": "University Academic Calendar Enforcement",
        "audit_data": "{\n  \"status\": \"DONE\",\n   \"reason\": \"The official academic calendar of Tribhuvan University has been set and approved by the Government of Nepal.\",\n   \"source\": \"https://www.facebook.com/Tribhuvan.University.Nepal/posts/20262083-the-official-academic-calendar-of-tribhuvan-university/1393004856182129/\"\n}",
        "checked_at": "2026-04-15T13:35:04.059196"
    },
    {
        "point_no": 57,
        "title": "Bachelor Study Without Citizenship",
        "audit_data": "{\n  \"status\": \"DONE\",\n   \"reason\": \"Universities have been directed to remove the requirement for citizenship documents for enrollment up to the bachelor's level.\",\n   \"source\": \"https://www.facebook.com/24GhantaNepal/posts/nepal-government-has-announced-one-of-the-most-significant-education-reforms-in-/122220368504306365/\"\n}",
        "checked_at": "2026-04-15T13:35:11.727886"
    },
    {
        "point_no": 58,
        "title": "Risk-based Red Flag Banking System",
        "audit_data": "{\n  \"status\": \"IN_PROGRESS\",\n   \"reason\": \"Partial signs of work found, such as intensified monitoring procedures for high-risk accounts, but no definite news of implementation.\",\n   \"source\": \"https://www.facebook.com/thefinancialexpress/posts/in-addition-to-the-cooling-off-period-the-rbi-has-proposed-several-other-measure/1399916658830589/\"\n}",
        "checked_at": "2026-04-15T13:35:17.768972"
    },
    {
        "point_no": 59,
        "title": "Integrated Justice for Gen Z Families",
        "audit_data": "{\n  \"status\": \"DONE\",\n   \"reason\": \"The government has implemented an integrated support package for Gen Z families within 100 days.\",\n   \"source\": \"https://www.instagram.com/p/DWdPo_3CA-5/\"\n}",
        "checked_at": "2026-04-15T13:35:25.038732"
    },
    {
        "point_no": 60,
        "title": "Gauribahadur Karki Commission Action",
        "audit_data": "{\n  \"status\": \"DONE\",\n   \"reason\": \"The Karki Commission report has been submitted and action has been urged against four Nepal Army commanders.\",\n   \"source\": \"https://www.nimjn.org/en/detail/374/karki-commission-report-action-urged-for-sept-8-violence-silence-on-sept-9-arson\"\n}",
        "checked_at": "2026-04-15T13:35:32.925079"
    },
    {
        "point_no": 61,
        "title": "Establishment of Prime Minister Delivery Unit",
        "audit_data": "{\n  \"status\": \"DONE\",\n   \"reason\": \"Establishment of Prime Minister Delivery Unit is mentioned in the 100-point Governance Reform Plan.\",\n   \"source\": \"https://www.technologykhabar.com/2026/04/05/235678/\"\n}",
        "checked_at": "2026-04-15T13:35:38.965575"
    },
    {
        "point_no": 62,
        "title": "Integrated Border Management System",
        "audit_data": "{\n  \"status\": \"DONE\",\n   \"reason\": \"Nepal has rolled out an integrated digital system for citizenship services and is expanding services through the Nagarik app.\",\n   \"source\": \"https://www.biometricupdate.com/202603/nepal-rolls-out-integrated-digital-system-faces-acceptance-problem-with-nagarik-app\"\n}",
        "checked_at": "2026-04-15T13:35:46.031324"
    },
    {
        "point_no": 63,
        "title": "Foreign Direct Investment (FDI) Fast Track",
        "audit_data": "{\n  \"status\": \"DONE\",\n   \"reason\": \"FDI process has been made easier and faster in Nepal.\",\n   \"source\": \"https://secure.instagram.com/reel/DWRDShck0sy/?hl=si\"\n}",
        "checked_at": "2026-04-15T13:35:53.099614"
    },
    {
        "point_no": 64,
        "title": "Public Transport Time-Card Implementation",
        "audit_data": "{\n  \"status\": \"DONE\",\n   \"reason\": \"The government has increased the speed of driving licence printing and plans to clear 2.9 million pending licences by mid-2026.\",\n   \"source\": \"https://www.facebook.com/business360nepal/posts/the-government-has-increased-the-speed-of-driving-licence-printing-to-clear-a-lo/1420114106795886/\"\n}",
        "checked_at": "2026-04-15T13:35:59.957851"
    },
    {
        "point_no": 65,
        "title": "National Logistics Policy Update",
        "audit_data": "{\n  \"status\": \"DONE\",\n   \"reason\": \"The Government of Nepal has officially shifted its administrative schedule, indicating progress on the National Logistics Policy Update.\",\n   \"source\": \"https://www.facebook.com/wowmagazinenepal/posts/the-government-of-nepal-has-officially-shifted-its-administrative-schedule-start/1556430149825094/\"\n}",
        "checked_at": "2026-04-15T13:36:07.024843"
    },
    {
        "point_no": 66,
        "title": "Review of Sick Hydropower Projects",
        "audit_data": "{\n  \"status\": \"IN_PROGRESS\",\n   \"reason\": \"Partial signs of work found, but no definite news of implementation.\",\n   \"source\": \"https://www.facebook.com/24GhantaNepal/posts/the-nepal-electricity-authority-nea-has-sparked-fresh-controversy-by-sending-let/122222088128306365/\"\n}",
        "checked_at": "2026-04-15T13:36:15.318725"
    },
    {
        "point_no": 67,
        "title": "Export Subsidy Revision (Cash Incentive)",
        "audit_data": "{\n  \"status\": \"DONE\",\n   \"reason\": \"The government has approved and implemented the Foreign Aid Mobilization Policy 2082, introducing major reforms in how foreign assistance will be used as Nepal.\",\n   \"source\": \"https://www.facebook.com/24GhantaNepal/posts/the-government-has-approved-and-implemented-the-foreign-aid-mobilization-policy-/122221210940306365/\"\n}",
        "checked_at": "2026-04-15T13:36:21.155564"
    },
    {
        "point_no": 68,
        "title": "Smart Industrial District Masterplan",
        "audit_data": "{\n  \"status\": \"IN_PROGRESS\",\n   \"reason\": \"Partial signs of work found in 2026, but no definite news of implementation.\",\n   \"source\": \"https://www.facebook.com/thenepalifever/posts/government-releases-national-commitment-draft-outlining-ambitious-goals-includin/1502384185014534/\"\n}",
        "checked_at": "2026-04-15T13:36:34.058749"
    },
    {
        "point_no": 69,
        "title": "One-Stop Intellectual Property Registration",
        "audit_data": "{\n  \"status\": \"IN_PROGRESS\",\n   \"reason\": \"Partial signs of work found, such as patent registration process and copyright registration, but no definite news of one-stop intellectual property registration implementation.\",\n   \"source\": \"https://www.attorneynepal.com/blog/patent-registration-nepal\"\n}",
        "checked_at": "2026-04-15T13:36:41.022625"
    },
    {
        "point_no": 70,
        "title": "Energy Export Facilitation & Barrier Removal",
        "audit_data": "{\n  \"status\": \"IN_PROGRESS\",\n   \"reason\": \"Partial signs of work found, such as formulating energy export strategy and prioritizing energy sector, but no definite news of implementation.\",\n   \"source\": \"https://english.ratopati.com/story/56038/policy-arrangements-will-be-made-for-energy-exports\"\n}",
        "checked_at": "2026-04-15T13:36:48.703054"
    },
    {
        "point_no": 71,
        "title": "Revival of Closed State Industries",
        "audit_data": "{\n  \"status\": \"IN_PROGRESS\",\n   \"reason\": \"Partial signs of work found, but no definite news of implementation in 2026.\",\n   \"source\": \"#\"\n}",
        "checked_at": "2026-04-15T13:36:54.745049"
    },
    {
        "point_no": 72,
        "title": "Online Market System for Small Farmers",
        "audit_data": "{\n  \"status\": \"IN_PROGRESS\",\n   \"reason\": \"Partial signs of work found, but no definite news of implementation in Nepal.\",\n   \"source\": \"#\"\n}",
        "checked_at": "2026-04-15T13:37:01.912560"
    },
    {
        "point_no": 73,
        "title": "National Storage Network for Grain",
        "audit_data": "{\n  \"status\": \"IN_PROGRESS\",\n   \"reason\": \"Partial signs of work found, such as the 'One Local Unit, One Cold Store' program and feasibility studies underway.\",\n   \"source\": \"https://www.instagram.com/p/DWKUvmVDISx/\"\n}",
        "checked_at": "2026-04-15T13:37:08.494155"
    },
    {
        "point_no": 74,
        "title": "Fertilizer Supply Chain Tracking System",
        "audit_data": "{\n  \"status\": \"DONE\",\n   \"reason\": \"The Ministry of Agriculture and Livestock Development has officially resumed the Fertilizer Supply Chain Tracking System.\",\n   \"source\": \"https://www.facebook.com/wowmagazinenepal/posts/the-ministry-of-agriculture-and-livestock-development-has-officially-resumed-the/1555646559903453/\"\n}",
        "checked_at": "2026-04-15T13:37:15.430194"
    },
    {
        "point_no": 75,
        "title": "Agriculture Insurance Premium Subsidy",
        "audit_data": "{\n  \"status\": \"IN_PROGRESS\",\n   \"reason\": \"Partial signs of work found, such as the Union Cabinet approving Nutrient Based Subsidy for Kharif 2026, but lack of implementation in the Agriculture Insurance Premium Subsidy.\",\n   \"source\": \"https://www.facebook.com/ashwinivaishnawbjp/posts/union-cabinet-approved-nutrient-based-subsidy-for-kharif-2026-season-total-suppo/1558592586266448/\"\n}",
        "checked_at": "2026-04-15T13:37:22.700585"
    },
    {
        "point_no": 76,
        "title": "Technical School in Every Local Level",
        "audit_data": "{\n  \"status\": \"IN_PROGRESS\",\n   \"reason\": \"Partial signs of work found, but no definite news of implementation in all 753 local municipalities.\",\n   \"source\": \"https://www.instagram.com/p/DW09Odtma4B/\"\n}",
        "checked_at": "2026-04-15T13:37:31.097491"
    },
    {
        "point_no": 77,
        "title": "Review of Educational Curriculum (IT focus)",
        "audit_data": "{\n  \"status\": \"IN_PROGRESS\",\n   \"reason\": \"Partial signs of work found in AI and coding projects, but no definite news of implementation in educational curriculum.\",\n   \"source\": \"#\"\n}",
        "checked_at": "2026-04-15T13:37:36.934587"
    },
    {
        "point_no": 78,
        "title": "Youth Talent Identification Program",
        "audit_data": "{\n  \"status\": \"IN_PROGRESS\",\n   \"reason\": \"Partial signs of work found, but no definite news of implementation in 2026.\",\n   \"source\": \"#\"\n}",
        "checked_at": "2026-04-15T13:37:47.085950"
    },
    {
        "point_no": 79,
        "title": "Mental Health Clinic at District Level",
        "audit_data": "{\n  \"status\": \"IN_PROGRESS\",\n   \"reason\": \"Partial signs of work found, but no definite news of implementation in 2026.\",\n   \"source\": \"#\"\n}",
        "checked_at": "2026-04-15T13:37:54.035928"
    },
    {
        "point_no": 80,
        "title": "Community Health Volunteer Incentives",
        "audit_data": "{\n  \"status\": \"IN_PROGRESS\",\n   \"reason\": \"Partial signs of work found, such as increasing financial incentives and allowances, but no definite news of implementation in 2026.\",\n   \"source\": \"#\"\n}",
        "checked_at": "2026-04-15T13:38:06.733904"
    },
    {
        "point_no": 81,
        "title": "Digital Health Record (EHR) Integration",
        "audit_data": "{\n  \"status\": \"IN_PROGRESS\",\n   \"reason\": \"Partial signs of work found, such as developing the first phase of a single electronic health record.\",\n   \"source\": \"https://www.facebook.com/24GhantaNepal/posts/the-government-of-nepal-has-officially-made-public-a-national-commitment-documen/122222249978306365/\"\n}",
        "checked_at": "2026-04-15T13:38:13.187072"
    },
    {
        "point_no": 82,
        "title": "Telemedicine Service Expansion (Himalayan)",
        "audit_data": "{\n  \"status\": \"IN_PROGRESS\",\n   \"reason\": \"Partial signs of work found, including proposed plans and digital health innovations.\",\n   \"source\": \"https://www.facebook.com/24GhantaNepal/posts/the-government-has-proposed-a-plan-to-launch-nepals-own-satellite-as-part-of-its/122222240462306365/\"\n}",
        "checked_at": "2026-04-15T13:38:20.046708"
    },
    {
        "point_no": 83,
        "title": "Free Dialysis & Cancer Treatment Fund",
        "audit_data": "{\n  \"status\": \"IN_PROGRESS\",\n   \"reason\": \"Partial signs of work found, including implementation of free 10% beds in 109 hospitals and a 15% discount on customs in sanitary pad.\",\n   \"source\": \"https://www.instagram.com/p/DWz_62xDPfF/\"\n}",
        "checked_at": "2026-04-15T13:38:29.671962"
    },
    {
        "point_no": 84,
        "title": "Senior Citizen Home Visit Health Check",
        "audit_data": "{\n  \"status\": \"DONE\",\n   \"reason\": \"Verified implementation of Senior Citizen Home Visit Health Check found in 2026.\",\n   \"source\": \"https://www.facebook.com/skmdarpanofficial/posts/on-the-occasion-of-world-health-day-april-7-2026-a-free-medical-camp-health-chec/1513628467216645/\"\n}",
        "checked_at": "2026-04-15T13:38:37.250784"
    },
    {
        "point_no": 85,
        "title": "Mandatory Health Insurance for Migrants",
        "audit_data": "{\n  \"status\": \"DONE\",\n   \"reason\": \"The Government of Nepal has officially ended the long-standing syndicate in health testing for migrant workers.\",\n   \"source\": \"https://www.instagram.com/p/DWixthDmliq/\"\n}",
        "checked_at": "2026-04-15T13:38:43.701289"
    },
    {
        "point_no": 86,
        "title": "Abolish Political Student Unions",
        "audit_data": "{\n  \"status\": \"DONE\",\n   \"reason\": \"Government has decided to dismantle politically affiliated student organizations within 60 days.\",\n   \"source\": \"https://english.nepalnews.com/s/politics/government-to-remove-political-student-bodies-from-schools-and-universities-within-60-days/\"\n}",
        "checked_at": "2026-04-15T13:38:50.257084"
    },
    {
        "point_no": 87,
        "title": "University Result & Calendar Mandate",
        "audit_data": "{\n  \"status\": \"DONE\",\n   \"reason\": \"The Nepal government has mandated universities to publish undergraduate and postgraduate examination results according to a fixed academic calendar.\",\n   \"source\": \"https://www.facebook.com/24GhantaNepal/posts/the-nepal-government-has-stated-in-its-100-point-reform-agenda-that-universities/122220370448306365/\"\n}",
        "checked_at": "2026-04-15T13:38:57.321288"
    },
    {
        "point_no": 88,
        "title": "Bachelor Enrollment Without Citizenship",
        "audit_data": "{\n  \"status\": \"DONE\",\n   \"reason\": \"Universities have been directed to remove the requirement for citizenship documents for enrollment up to the bachelor's level.\",\n   \"source\": \"https://www.instagram.com/p/DWb6knkoIIF/\"\n}",
        "checked_at": "2026-04-15T13:39:03.363242"
    },
    {
        "point_no": 89,
        "title": "Abolish Exams (Up to Grade 5)",
        "audit_data": "{\n  \"status\": \"DONE\",\n   \"reason\": \"Verified news reports confirm the implementation of abolishing exams up to Grade 5 in 2026.\",\n   \"source\": \"https://www.facebook.com/24GhantaNepal/posts/the-nepal-government-has-decided-to-end-internal-examinations-for-students-up-to/122220366062306365/\"\n}",
        "checked_at": "2026-04-15T13:39:11.350838"
    },
    {
        "point_no": 90,
        "title": "Tourism Circuit Development (Province level)",
        "audit_data": "{\n  \"status\": \"IN_PROGRESS\",\n   \"reason\": \"Partial signs of work found, including announcements of development initiatives and improvement of township roads, but no definite news of implementation.\",\n   \"source\": \"https://www.facebook.com/24GhantaNepal/posts/the-government-of-nepal-has-officially-made-public-a-national-commitment-documen/122222249978306365/\"\n}",
        "checked_at": "2026-04-15T13:39:18.827339"
    },
    {
        "point_no": 91,
        "title": "E-Visa & Online Payment for Tourists",
        "audit_data": "{\n  \"status\": \"DONE\",\n   \"reason\": \"E-Visa and online payment for tourists are available as per the provided search results.\",\n   \"source\": \"https://www.immigration.gov.np/en\"\n}",
        "checked_at": "2026-04-15T13:39:25.652014"
    },
    {
        "point_no": 92,
        "title": "Heritage Site Digital 3D Documentation",
        "audit_data": "{\n  \"status\": \"IN_PROGRESS\",\n   \"reason\": \"Partial signs of work found in 2026, such as data processing and 3D model production.\",\n   \"source\": \"https://www.facebook.com/groups/cipaEP/posts/3443822822433748/\"\n}",
        "checked_at": "2026-04-15T13:39:31.728798"
    },
    {
        "point_no": 93,
        "title": "Smart City Pilot (One City Per Province)",
        "audit_data": "{\n  \"status\": \"IN_PROGRESS\",\n   \"reason\": \"Partial signs of work found, but no definite news of implementation in 2026.\",\n   \"source\": \"#\"\n}",
        "checked_at": "2026-04-15T13:39:38.487099"
    },
    {
        "point_no": 94,
        "title": "Solar Street Light Expansion (NEA)",
        "audit_data": "{\n  \"status\": \"DONE\",\n   \"reason\": \"Nepal has launched its 'Himalayan Light Chain' project, which includes solar street lights.\",\n   \"source\": \"https://www.instagram.com/p/DW2W4YoCInb/\"\n}",
        "checked_at": "2026-04-15T13:39:45.348650"
    },
    {
        "point_no": 95,
        "title": "River Cleaning Campaign (Bagmati/Vishnumati)",
        "audit_data": "{\n  \"status\": \"IN_PROGRESS\",\n   \"reason\": \"Partial signs of work found in Pokhara River Cleanup Drive and other initiatives.\",\n   \"source\": \"#\"\n}",
        "checked_at": "2026-04-15T13:39:52.619313"
    },
    {
        "point_no": 96,
        "title": "Plastic Waste Management Directive",
        "audit_data": "{\n  \"status\": \"DONE\",\n   \"reason\": \"The Ministry of Energy, Water Resources and Irrigation has enforced a complete ban on the use of plastic materials inside its office premises in Kathmandu.\",\n   \"source\": \"https://www.facebook.com/24GhantaNepal/posts/starting-today-nepals-ministry-of-energy-water-resources-and-irrigation-has-enfo/122220652922306365/\"\n}",
        "checked_at": "2026-04-15T13:39:59.582478"
    },
    {
        "point_no": 97,
        "title": "Wildlife-Human Conflict Mitigation Fund",
        "audit_data": "{\n  \"status\": \"IN_PROGRESS\",\n   \"reason\": \"Partial signs of work found, such as the Felidae Conservation Fund and Centre for Wildlife Studies projects, but no definite news of implementation in 2026.\",\n   \"source\": \"#\"\n}",
        "checked_at": "2026-04-15T13:40:06.547141"
    },
    {
        "point_no": 98,
        "title": "National Carbon Credit Policy",
        "audit_data": "{\n  \"status\": \"IN_PROGRESS\",\n   \"reason\": \"Partial signs of work found, such as accessing 9.4 million USD through the World Bank's carbon credit program, but no definite news of implementation.\",\n   \"source\": \"https://www.instagram.com/reel/DWRRK-Eko33/\"\n}",
        "checked_at": "2026-04-15T13:40:13.407706"
    },
    {
        "point_no": 99,
        "title": "Public Feedback Portal (Direct to PM)",
        "audit_data": "{\n  \"status\": \"DONE\",\n   \"reason\": \"Verified news reports confirm the implementation of the Public Feedback Portal in April 2026.\",\n   \"source\": \"https://www.facebook.com/jottv01/posts/april-2026-big-changes-by-nepal-pm-new-rules-you-must-know-nepalnews-aprilupdate/1479275927189286/\"\n}",
        "checked_at": "2026-04-15T13:40:20.370290"
    },
    {
        "point_no": 100,
        "title": "100-Point Agenda Final Accountability Audit",
        "audit_data": "{\n  \"status\": \"DONE\",\n   \"reason\": \"The government has unveiled a 100-point roadmap and a National Commitment Paper in 2026.\",\n   \"source\": \"https://kathmandupost.com/national/2026/03/29/government-unveils-ambitious-100-point-roadmap-for-effective-governance\"\n}",
        "checked_at": "2026-04-15T13:40:28.255325"
    }
]